AtomicDecode.py
atomicdecode-1.2.dist-info/LICENSE
atomicdecode-1.2.dist-info/METADATA
atomicdecode-1.2.dist-info/WHEEL
atomicdecode-1.2.dist-info/RECORD
